{
  "parent": "minecraft:recipes/root",
  "criteria": {
    "has_echo_amethyst_ingot": {
      "conditions": {
        "items": [
          {
            "items": [
              "deathcube:echo_amethyst_ingot"
            ]
          }
        ]
      },
      "trigger": "minecraft:inventory_changed"
    },
    "has_the_recipe": {
      "conditions": {
        "recipe": "deathcube:echo_amethyst_block"
      },
      "trigger": "minecraft:recipe_unlocked"
    }
  },
  "requirements": [
    [
      "has_echo_amethyst_ingot",
      "has_the_recipe"
    ]
  ],
  "rewards": {
    "recipes": [
      "deathcube:echo_amethyst_block"
    ]
  }
}